cip_workflow_status/__init__.py
cip_workflow_status/file_type.py
cip_workflow_status/ladder_type.py
cip_workflow_status/transcoder_name.py
cip_workflow_status/workflow_status.py
cip_workflow_status-0.0.19.dist-info/METADATA
cip_workflow_status-0.0.19.dist-info/WHEEL
cip_workflow_status-0.0.19.dist-info/top_level.txt
cip_workflow_status-0.0.19.dist-info/RECORD
