Metadata-Version: 2.1
Name: cip-workflow-status
Version: 0.0.19
Summary: Workflow Status.
Home-page: UNKNOWN
Author: Fábio Pereira
Author-email: fabio.pereira@tvlgobo.com.br
License: MIT
Platform: UNKNOWN
